AUTHORS
CHANGELOG.md
LICENSE
MANIFEST.in
README.md
setup.py
django_tailordev_contact.egg-info/PKG-INFO
django_tailordev_contact.egg-info/SOURCES.txt
django_tailordev_contact.egg-info/dependency_links.txt
django_tailordev_contact.egg-info/not-zip-safe
django_tailordev_contact.egg-info/top_level.txt
td_contact/__init__.py
td_contact/forms.py
td_contact/models.py
td_contact/settings.py
td_contact/test_urls.py
td_contact/tests.py
td_contact/urls.py
td_contact/utils.py
td_contact/views.py
td_contact/locale/en/LC_MESSAGES/django.mo
td_contact/locale/en/LC_MESSAGES/django.po
td_contact/locale/fr/LC_MESSAGES/django.mo
td_contact/locale/fr/LC_MESSAGES/django.po
td_contact/templates/contact/form.html
td_contact/templates/contact/partials/aside.html
td_contact/templates/contact/partials/contact_recipient.html