Metadata-Version: 1.1
Name: django-tailordev-contact
Version: 0.5.0
Summary: Django TailorDev Contact  A simple contact form for your django projects.
Home-page: https://bitbucket.org/tailordev/django-tailordev-contact
Author: Julien Maupetit
Author-email: julien@tailordev.com
License: MIT
Platform: UNKNOWN
Classifier: Topic :: Internet :: WWW/HTTP :: Dynamic Content
Classifier: Intended Audience :: Developers
Classifier: Programming Language :: Python
Classifier: Programming Language :: Python :: 2
Classifier: Programming Language :: Python :: 2.6
Classifier: Programming Language :: Python :: 2.7
Classifier: Programming Language :: Python :: 3
Classifier: Programming Language :: Python :: 3.3
Classifier: Programming Language :: Python :: 3.4
Classifier: Framework :: Django
Classifier: Development Status :: 4 - Beta
Classifier: Operating System :: OS Independent
